langchain_2ly/__init__.py
langchain_2ly/mcp.py
langchain_2ly/mcp_only.py
langchain_2ly-0.0.1.dist-info/licenses/LICENSE
langchain_2ly-0.0.1.dist-info/METADATA
langchain_2ly-0.0.1.dist-info/WHEEL
langchain_2ly-0.0.1.dist-info/top_level.txt
langchain_2ly-0.0.1.dist-info/RECORD
