Metadata-Version: 2.4
Name: langchain_2ly
Version: 0.0.1
Summary: 2ly python module providing helpers to quickly connect 2ly to your agents in Python.
Author-email: Eiger AI <eiger@alpinai.ch>
License: Apache-2.0
Project-URL: Homepage, https://github.com/alpinai/2ly
Project-URL: Issues, https://github.com/alpinai/2ly/issues
Requires-Python: >=3.10
License-File: LICENSE
Requires-Dist: mcp
Requires-Dist: langchain-core
Requires-Dist: langchain-mcp-adapters
Provides-Extra: dev
Requires-Dist: pytest>=7.0; extra == "dev"
Requires-Dist: pytest-asyncio>=0.21; extra == "dev"
Requires-Dist: build>=0.10; extra == "dev"
Requires-Dist: twine>=5.0; extra == "dev"
Provides-Extra: examples
Requires-Dist: langgraph>=0.2.0; extra == "examples"
Requires-Dist: langchain-openai>=0.2.0; extra == "examples"
Requires-Dist: pydantic>=2.0.0; extra == "examples"
Requires-Dist: python-dotenv>=1.0.0; extra == "examples"
Provides-Extra: all
Requires-Dist: langchain_2ly[dev]; extra == "all"
Requires-Dist: langchain_2ly[examples]; extra == "all"
Dynamic: license-file
